shellsnmp/Poller.py
shellsnmp/__init__.py
shellsnmp-0.1.7.dist-info/DESCRIPTION.rst
shellsnmp-0.1.7.dist-info/METADATA
shellsnmp-0.1.7.dist-info/RECORD
shellsnmp-0.1.7.dist-info/WHEEL
shellsnmp-0.1.7.dist-info/metadata.json
shellsnmp-0.1.7.dist-info/top_level.txt
