Metadata-Version: 2.0
Name: shellsnmp
Version: 0.1.7
Summary: UNKNOWN
Home-page: http://github.com/mpenning/shellsnmp/
Author: David Michael Pennington
Author-email: mike@pennington.net
License: MIT
Keywords: Python snmp using shell calls
Platform: any
Classifier: Development Status :: 5 - Production/Stable
Classifier: Environment :: Plugins
Classifier: Intended Audience :: Developers
Classifier: Intended Audience :: System Administrators
Classifier: Intended Audience :: Information Technology
Classifier: Intended Audience :: Telecommunications Industry
Classifier: License :: OSI Approved :: GNU General Public License (GPL)
Classifier: Natural Language :: English
Classifier: Operating System :: OS Independent
Classifier: Programming Language :: Python
Classifier: Topic :: Communications
Classifier: Topic :: Internet
Classifier: Topic :: System :: Networking
Classifier: Topic :: System :: Networking :: Monitoring
Classifier: Topic :: Software Development :: Libraries :: Python Modules
Requires-Dist: arrow
